googledrivedl/__init__.py
googledrivedl/googledrivedl.py
googledrivedl-0.1.0.dist-info/METADATA
googledrivedl-0.1.0.dist-info/WHEEL
googledrivedl-0.1.0.dist-info/licenses/LICENSE
googledrivedl-0.1.0.dist-info/RECORD
