Metadata-Version: 2.1
Name: googledrivedl
Version: 0.1.0
Summary: Python library that allows you to download Google Drive files and folders.
Project-URL: Homepage, https://github.com/duckduckgrayduck/googledrivedl
Project-URL: Bug Tracker, https://github.com/duckduckgrayduck/googledrivedl/issues
Author-email: duckduckgrayduck <sanjin+googledrivedl@muckrock.com>
License-File: LICENSE
Classifier: License :: OSI Approved :: MIT License
Classifier: Operating System :: OS Independent
Classifier: Programming Language :: Python :: 3
Requires-Python: >=3.7
Requires-Dist: html-parser
